README.md
setup.py
bohrium_openapi_python_sdk.egg-info/PKG-INFO
bohrium_openapi_python_sdk.egg-info/SOURCES.txt
bohrium_openapi_python_sdk.egg-info/dependency_links.txt
bohrium_openapi_python_sdk.egg-info/entry_points.txt
bohrium_openapi_python_sdk.egg-info/top_level.txt
sdk/__init__.py
sdk/node.py