Metadata-Version: 2.1
Name: bohrium-openapi-python-sdk
Version: 0.0.2
Summary: bohrium openapi python sdk
Home-page: https://github.com/dingzhoahan
Author: dingzhaohan
Author-email: dingzh@dp.tech
Requires-Python: >=3.7
